pyressim/__init__.py
pyressim/boundary_conditions.py
pyressim/fluid.py
pyressim/grid.py
pyressim/lithology.py
pyressim/multiphase.py
pyressim/reservoir.py
pyressim/rock_physics.py
pyressim/solver.py
pyressim/source_sink.py
pyressim/time_stepping.py
pyressim/utils.py
pyressim/visualization.py
pyressim/well.py
pyressim-0.1.0.dist-info/METADATA
pyressim-0.1.0.dist-info/WHEEL
pyressim-0.1.0.dist-info/top_level.txt
pyressim-0.1.0.dist-info/RECORD
